napari_nucleaizer/__init__.py
napari_nucleaizer/common_stuff.py
napari_nucleaizer/config_loader.py
napari_nucleaizer/image_transform.py
napari_nucleaizer/model_db.py
napari_nucleaizer/model_selector_widget.py
napari_nucleaizer/napari.yaml
napari_nucleaizer/nucleaizer_widget.py
napari_nucleaizer/prediction_widget.py
napari_nucleaizer/training_widget.py
napari_nucleaizer-0.2.5.dist-info/LICENSE
napari_nucleaizer-0.2.5.dist-info/METADATA
napari_nucleaizer-0.2.5.dist-info/WHEEL
napari_nucleaizer-0.2.5.dist-info/entry_points.txt
napari_nucleaizer-0.2.5.dist-info/top_level.txt
napari_nucleaizer-0.2.5.dist-info/RECORD
