Metadata-Version: 2.1
Name: napari-nucleaizer
Version: 0.2.5
Summary: A GUI interface for training and prediction using the nucleAIzer nuclei detection method.
Home-page: https://github.com/etasnadi/napari_nucleaizer
Author: Ervin Tasnadi
Author-email: tasnadi.ervin@brc.hu
License: BSD-3
Project-URL: Bug Tracker, https://github.com/etasnadi/napari_nucleaizer/issues
Project-URL: Documentation, https://napari-nucleaizer-docs.readthedocs.io/en/latest/index.html
Project-URL: Source Code, https://github.com/etasnadi/napari_nucleaizer
Project-URL: User Support, https://github.com/etasnadi/napari_nucleaizer/issues
Classifier: Development Status :: 3 - Alpha
Classifier: Intended Audience :: Developers
Classifier: Framework :: napari
Classifier: Programming Language :: Python
Classifier: Programming Language :: Python :: 3
Classifier: Programming Language :: Python :: 3.8
Classifier: Programming Language :: Python :: 3.9
Classifier: Programming Language :: Python :: 3.10
Classifier: Operating System :: OS Independent
Classifier: License :: OSI Approved :: BSD License
Requires-Python: >=3.8
License-File: LICENSE
Requires-Dist: napari
Requires-Dist: qtpy
Requires-Dist: jsonpickle
Requires-Dist: numpy
Requires-Dist: scikit-image
Requires-Dist: imageio
Requires-Dist: nucleaizer-backend
